write_config_files/__init__.py
write_config_files/cli.py
write_config_files/config.py
write_config_files/files.py
write_config_files/logging.py
write_config_files/printers.py
write_config_files/rendering.py
write_config_files/commands/__init__.py
write_config_files/commands/diff.py
write_config_files/commands/write.py
write_config_files-0.4.0.dist-info/LICENSE
write_config_files-0.4.0.dist-info/METADATA
write_config_files-0.4.0.dist-info/WHEEL
write_config_files-0.4.0.dist-info/entry_points.txt
write_config_files-0.4.0.dist-info/top_level.txt
write_config_files-0.4.0.dist-info/RECORD
