Metadata-Version: 2.1
Name: write_config_files
Version: 0.4.0
Summary: render and write out templated config files
Author: Samuel Searles-Bryant
Author-email: sam@samueljsb.co.uk
License: MIT
Project-URL: Source, https://github.com/samueljsb/write-config-files
Project-URL: Changelog, https://github.com/samueljsb/write-config-files/blob/main/CHANGELOG.md
Classifier: License :: OSI Approved :: MIT License
Classifier: Programming Language :: Python :: 3
Classifier: Programming Language :: Python :: 3 :: Only
Classifier: Programming Language :: Python :: Implementation :: CPython
Requires-Python: >=3.8
License-File: LICENSE
Requires-Dist: Jinja2
Requires-Dist: PyYAML
Requires-Dist: attrs
